wagtail_app_pages/__init__.py
wagtail_app_pages/apps.py
wagtail_app_pages/models.py
wagtail_app_pages/templatetags/__init__.py
wagtail_app_pages/templatetags/app_pages_tags.py
wagtail_app_pages-0.2.1.dist-info/DESCRIPTION.rst
wagtail_app_pages-0.2.1.dist-info/METADATA
wagtail_app_pages-0.2.1.dist-info/RECORD
wagtail_app_pages-0.2.1.dist-info/WHEEL
wagtail_app_pages-0.2.1.dist-info/metadata.json
wagtail_app_pages-0.2.1.dist-info/top_level.txt
