Metadata-Version: 2.0
Name: wagtail-app-pages
Version: 0.2.1
Summary: Full MVC support for wagtail pages
Home-page: https://github.com/mwesterhof/wagtail_app_pages
Author: Marco Westerhof
Author-email: westerhof.marco@gmail.com
License: MIT license
Keywords: wagtail_app_pages
Platform: UNKNOWN
Classifier: Development Status :: 4 - Beta
Classifier: Intended Audience :: Developers
Classifier: License :: OSI Approved :: MIT License
Classifier: Natural Language :: English
Classifier: Programming Language :: Python :: 2
Classifier: Programming Language :: Python :: 2.7
Classifier: Programming Language :: Python :: 3
Classifier: Programming Language :: Python :: 3.4
Classifier: Programming Language :: Python :: 3.5
Classifier: Programming Language :: Python :: 3.6
Requires-Dist: wagtail (<2.1,>=2.0)
